.gitignore
LICENSE.md
README.md
setup.py
.github/workflows/pypi-publish.yml
pymetaverse/__init__.py
pymetaverse/bot.py
pymetaverse/const.py
pymetaverse/eventtarget.py
pymetaverse/httpclient.py
pymetaverse/llsd.py
pymetaverse/login.py
pymetaverse.egg-info/PKG-INFO
pymetaverse.egg-info/SOURCES.txt
pymetaverse.egg-info/dependency_links.txt
pymetaverse.egg-info/top_level.txt
pymetaverse/viewer/__init__.py
pymetaverse/viewer/agent.py
pymetaverse/viewer/circuit.py
pymetaverse/viewer/message_template.msg
pymetaverse/viewer/message_template.msg.sha1
pymetaverse/viewer/messages.py
pymetaverse/viewer/packet.py
pymetaverse/viewer/region.py
pymetaverse/viewer/simulator.py